stack_it/__init__.py
stack_it/admin.py
stack_it/apps.py
stack_it/models.py
stack_it/translation.py
stack_it/urls.py
stack_it/views.py
stack_it/blocks/__init__.py
stack_it/blocks/models.py
stack_it/contents/__init__.py
stack_it/contents/abstracts.py
stack_it/contents/admin.py
stack_it/contents/models/__init__.py
stack_it/contents/models/pages.py
stack_it/contents/models/templates.py
stack_it/images/__init__.py
stack_it/images/admin.py
stack_it/images/autocomplete.py
stack_it/images/forms.py
stack_it/images/mixins.py
stack_it/images/models.py
stack_it/menus/__init__.py
stack_it/menus/models.py
stack_it/menus/translation.py
stack_it/migrations/0001_initial.py
stack_it/migrations/0002_meta_description.py
stack_it/migrations/0003_key.py
stack_it/migrations/0004_auto_20190813_0656.py
stack_it/migrations/0005_page_main_site.py
stack_it/migrations/0006_auto_20190814_0833.py
stack_it/migrations/0007_auto_20190814_0925.py
stack_it/migrations/0008_page_priority.py
stack_it/migrations/0009_page_changefreq.py
stack_it/migrations/0010_page_date_updated.py
stack_it/migrations/__init__.py
stack_it/pages/__init__.py
stack_it/pages/managers.py
stack_it/pages/models.py
stack_it/seo/__init__.py
stack_it/seo/helpers.py
stack_it/seo/mixins.py
stack_it/seo/models.py
stack_it/static/admin/css/dropzone.css
stack_it/static/admin/css/mediamanager.css
stack_it/static/admin/img/eye.svg
stack_it/static/admin/img/file-o.svg
stack_it/static/admin/img/pencil.svg
stack_it/static/admin/img/trash-o.svg
stack_it/static/admin/js/autocomplete.js
stack_it/static/admin/js/dropzone.js
stack_it/static/admin/js/mediamanager.js
stack_it/static/css/stack_it.css
stack_it/static/js/stack_it.js
stack_it/templates/admin/polymorphic/edit_inline/tabular.html
stack_it/templates/admin/stack_it/image/change_list.html
stack_it/templates/admin/stack_it/image/change_list_results.html
stack_it/templates/admin/stack_it/image/folder_select.html
stack_it/templates/stack_it/base.html
stack_it/templates/stack_it/editable.html
django_stack_it_bak-0.1.13.2.dist-info/AUTHORS.rst
django_stack_it_bak-0.1.13.2.dist-info/LICENSE
django_stack_it_bak-0.1.13.2.dist-info/METADATA
django_stack_it_bak-0.1.13.2.dist-info/WHEEL
django_stack_it_bak-0.1.13.2.dist-info/top_level.txt
django_stack_it_bak-0.1.13.2.dist-info/RECORD
